datasette_sql_scraper/__init__.py
datasette_sql_scraper-0.1.dist-info/DESCRIPTION.rst
datasette_sql_scraper-0.1.dist-info/METADATA
datasette_sql_scraper-0.1.dist-info/RECORD
datasette_sql_scraper-0.1.dist-info/WHEEL
datasette_sql_scraper-0.1.dist-info/entry_points.txt
datasette_sql_scraper-0.1.dist-info/metadata.json
datasette_sql_scraper-0.1.dist-info/top_level.txt
